MANIFEST.in
README.rst
setup.py
collective/.DS_Store
collective/__init__.py
collective/__init__.pyc
collective.ptg.uigallery.egg-info/PKG-INFO
collective.ptg.uigallery.egg-info/SOURCES.txt
collective.ptg.uigallery.egg-info/dependency_links.txt
collective.ptg.uigallery.egg-info/entry_points.txt
collective.ptg.uigallery.egg-info/namespace_packages.txt
collective.ptg.uigallery.egg-info/not-zip-safe
collective.ptg.uigallery.egg-info/requires.txt
collective.ptg.uigallery.egg-info/top_level.txt
collective/ptg/.DS_Store
collective/ptg/__init__.py
collective/ptg/__init__.pyc
collective/ptg/uigallery/.DS_Store
collective/ptg/uigallery/__init__.py
collective/ptg/uigallery/__init__.pyc
collective/ptg/uigallery/configure.zcml
collective/ptg/uigallery/i18n.sh
collective/ptg/uigallery/uigallery.pt
collective/ptg/uigallery/locales/.DS_Store
collective/ptg/uigallery/resources/no_style.css
collective/ptg/uigallery/resources/style.css
docs/HISTORY.txt
docs/INSTALL.txt
docs/LICENSE.GPL
docs/LICENSE.txt