Metadata-Version: 1.0
Name: collective.ptg.uigallery
Version: 0.1.1
Summary: uigallery for plonetruegallery
Home-page: https://github.com/collective/collective.ptg.uigallery
Author: Espen Moe-Nilssen
Author-email: espen@medialog.no
License: GPL
Keywords: plonetruegallery gallery plone addon
Platform: UNKNOWN
Classifier: Framework :: Plone
Classifier: Programming Language :: Python
